lightnovel_crawler_patiorjunrick-4.0.1.dist-info/licenses/LICENSE
lncrawl/VERSION
lncrawl/__init__.py
lncrawl/__main__.py
lncrawl/app.py
lncrawl/config.py
lncrawl/context.py
lncrawl/exceptions.py
lncrawl/assets/__init__.py
lncrawl/assets/banner.py
lncrawl/assets/colors.py
lncrawl/assets/icons.py
lncrawl/assets/languages.py
lncrawl/assets/user_agents.py
lncrawl/assets/version.py
lncrawl/assets/emails/__init__.py
lncrawl/assets/emails/full_novel.html.j2
lncrawl/assets/emails/job_status.html.j2
lncrawl/assets/emails/layout.html.j2
lncrawl/assets/emails/otp.html.j2
lncrawl/assets/emails/repass.html.j2
lncrawl/assets/epub/__init__.py
lncrawl/assets/epub/chapter.xhtml
lncrawl/assets/epub/cover.xhtml
lncrawl/assets/epub/style.css
lncrawl/assets/images/__init__.py
lncrawl/assets/images/favicon.ico
lncrawl/cloudscraper/__init__.py
lncrawl/cloudscraper/cloudflare.py
lncrawl/cloudscraper/cloudflare_v2.py
lncrawl/cloudscraper/cloudflare_v3.py
lncrawl/cloudscraper/exceptions.py
lncrawl/cloudscraper/help.py
lncrawl/cloudscraper/proxy_manager.py
lncrawl/cloudscraper/stealth.py
lncrawl/cloudscraper/turnstile.py
lncrawl/cloudscraper/captcha/2captcha.py
lncrawl/cloudscraper/captcha/9kw.py
lncrawl/cloudscraper/captcha/__init__.py
lncrawl/cloudscraper/captcha/anticaptcha.py
lncrawl/cloudscraper/captcha/capmonster.py
lncrawl/cloudscraper/captcha/capsolver.py
lncrawl/cloudscraper/captcha/deathbycaptcha.py
lncrawl/cloudscraper/interpreters/__init__.py
lncrawl/cloudscraper/interpreters/chakracore.py
lncrawl/cloudscraper/interpreters/encapsulated.py
lncrawl/cloudscraper/interpreters/js2py.py
lncrawl/cloudscraper/interpreters/js2py_interpreter.py
lncrawl/cloudscraper/interpreters/jsunfuck.py
lncrawl/cloudscraper/interpreters/native.py
lncrawl/cloudscraper/interpreters/nodejs.py
lncrawl/cloudscraper/interpreters/v8.py
lncrawl/cloudscraper/user_agent/__init__.py
lncrawl/cloudscraper/user_agent/browsers.json
lncrawl/commands/__init__.py
lncrawl/commands/config.py
lncrawl/commands/crawl.py
lncrawl/commands/search.py
lncrawl/commands/server.py
lightnovel_crawler_patiorjunrick-4.0.1.dist-info/METADATA
lightnovel_crawler_patiorjunrick-4.0.1.dist-info/WHEEL
lightnovel_crawler_patiorjunrick-4.0.1.dist-info/entry_points.txt
lightnovel_crawler_patiorjunrick-4.0.1.dist-info/top_level.txt
lightnovel_crawler_patiorjunrick-4.0.1.dist-info/RECORD
